README.rst
setup.py
src/alibaba_cloud_secretsmanager_client/__init__.py
src/alibaba_cloud_secretsmanager_client/cache_client_builder.py
src/alibaba_cloud_secretsmanager_client/secret_manager_cache_client.py
src/alibaba_cloud_secretsmanager_client/secret_manager_cache_client_builder.py
src/alibaba_cloud_secretsmanager_client/auth/__init__.py
src/alibaba_cloud_secretsmanager_client/auth/client_key_signer.py
src/alibaba_cloud_secretsmanager_client/cache/__init__.py
src/alibaba_cloud_secretsmanager_client/cache/cache_secret_store_strategy.py
src/alibaba_cloud_secretsmanager_client/cache/default_secret_cache_hook.py
src/alibaba_cloud_secretsmanager_client/cache/file_cache_secret_store_strategy.py
src/alibaba_cloud_secretsmanager_client/cache/memory_cache_secret_store_strategy.py
src/alibaba_cloud_secretsmanager_client/cache/secret_cache_hook.py
src/alibaba_cloud_secretsmanager_client/model/__init__.py
src/alibaba_cloud_secretsmanager_client/model/client_key_credentials.py
src/alibaba_cloud_secretsmanager_client/model/credentials_properties.py
src/alibaba_cloud_secretsmanager_client/model/dkms_config.py
src/alibaba_cloud_secretsmanager_client/model/region_info.py
src/alibaba_cloud_secretsmanager_client/model/secret_info.py
src/alibaba_cloud_secretsmanager_client/service/__init__.py
src/alibaba_cloud_secretsmanager_client/service/back_off_strategy.py
src/alibaba_cloud_secretsmanager_client/service/default_refresh_secret_strategy.py
src/alibaba_cloud_secretsmanager_client/service/default_secret_manager_client_builder.py
src/alibaba_cloud_secretsmanager_client/service/full_jitter_back_off_strategy.py
src/alibaba_cloud_secretsmanager_client/service/refresh_secret_strategy.py
src/alibaba_cloud_secretsmanager_client/service/secret_manager_client.py
src/alibaba_cloud_secretsmanager_client/service/user_agent_manager.py
src/alibaba_cloud_secretsmanager_client/utils/__init__.py
src/alibaba_cloud_secretsmanager_client/utils/aes_utils.py
src/aliyun_secret_manager_client.egg-info/PKG-INFO
src/aliyun_secret_manager_client.egg-info/SOURCES.txt
src/aliyun_secret_manager_client.egg-info/dependency_links.txt
src/aliyun_secret_manager_client.egg-info/requires.txt
src/aliyun_secret_manager_client.egg-info/top_level.txt
