Metadata-Version: 1.2
Name: aliyun-secret-manager-client
Version: 0.1.1
Summary: Alibaba Cloud Secrets Manager Client implementation for Python
Home-page: UNKNOWN
Author: Alibaba Cloud
Maintainer: Alibaba Cloud
License: Apache License 2.0
Keywords: aliyun,kms,secrets-manager
Platform: UNKNOWN
Classifier: Development Status :: 5 - Production/Stable
Classifier: Programming Language :: Python
Classifier: Programming Language :: Python :: 2
Classifier: Programming Language :: Python :: 2.7
Classifier: Programming Language :: Python :: 3
Classifier: Programming Language :: Python :: 3.4
Classifier: Programming Language :: Python :: 3.5
Classifier: Programming Language :: Python :: 3.6
Classifier: Programming Language :: Python :: 3.7
Classifier: Programming Language :: Python :: Implementation :: CPython
Classifier: Topic :: Security
